example_project
prefixed_textinput
