Metadata-Version: 2.4
Name: django-prefixed-textinput
Version: 1.0.1
Summary: An extension of the default TextInput widget that displays a read-only string prefix
Home-page: http://github.com/BigglesZX/django-prefixed-textinput
Author: James Tiplady
Maintainer: James Tiplady
License: MIT
Keywords: django
Platform: OS Independent
Classifier: Development Status :: 5 - Production/Stable
Classifier: Environment :: Web Environment
Classifier: Intended Audience :: Developers
Classifier: License :: OSI Approved :: MIT License
Classifier: Operating System :: OS Independent
Classifier: Programming Language :: Python
Classifier: Programming Language :: Python :: 3.8
Classifier: Programming Language :: Python :: 3.9
Classifier: Programming Language :: Python :: 3.10
Classifier: Programming Language :: Python :: 3.11
Classifier: Programming Language :: Python :: 3.12
Classifier: Programming Language :: Python :: 3.13
Classifier: Programming Language :: Python :: 3.14
Classifier: Topic :: Software Development :: Libraries :: Python Modules
Classifier: Topic :: Software Development :: Libraries :: Application Frameworks
Classifier: Framework :: Django
Classifier: Framework :: Django :: 4.2
Classifier: Framework :: Django :: 5.0
Classifier: Framework :: Django :: 5.1
Classifier: Framework :: Django :: 5.2
Requires-Python: >=3.8,<4
License-File: LICENSE
Requires-Dist: Django>=4.2
Provides-Extra: dev
Requires-Dist: black~=25.9.0; extra == "dev"
Requires-Dist: Django~=5.2.8; extra == "dev"
Requires-Dist: flake8~=7.3.0; extra == "dev"
Requires-Dist: setuptools~=80.9.0; extra == "dev"
Requires-Dist: tox~=4.32.0; extra == "dev"
Requires-Dist: twine~=6.2.0; extra == "dev"
Requires-Dist: wheel~=0.45.1; extra == "dev"
Dynamic: author
Dynamic: classifier
Dynamic: description
Dynamic: description-content-type
Dynamic: home-page
Dynamic: keywords
Dynamic: license
Dynamic: license-file
Dynamic: maintainer
Dynamic: platform
Dynamic: provides-extra
Dynamic: requires-dist
Dynamic: requires-python
Dynamic: summary
